beetsplug/ibroadcast/__init__.py
beetsplug/ibroadcast/about.py
beetsplug/ibroadcast/command.py
beetsplug/ibroadcast/common.py
beetsplug/ibroadcast/config_default.yml
beets_ibroadcast-0.5.2.dist-info/METADATA
beets_ibroadcast-0.5.2.dist-info/NOTICE
beets_ibroadcast-0.5.2.dist-info/WHEEL
beets_ibroadcast-0.5.2.dist-info/top_level.txt
beets_ibroadcast-0.5.2.dist-info/RECORD
