Metadata-Version: 2.1
Name: beets-ibroadcast
Version: 0.5.2
Summary: iBroadcast plugin for Beets
Home-page: https://github.com/ctrueden/beets-ibroadcast
Author: Curtis Rueden
Author-email: ctrueden@gmail.com
License: Unlicense
Platform: ALL
Classifier: Topic :: Multimedia :: Sound/Audio
Classifier: License :: CC0 1.0 Universal (CC0 1.0) Public Domain Dedication
Classifier: Environment :: Console
Classifier: Programming Language :: Python :: 3
Classifier: Programming Language :: Python :: 3.6
Classifier: Programming Language :: Python :: 3.7
Classifier: Programming Language :: Python :: 3.8
Requires-Python: >=3.6
License-File: NOTICE
Requires-Dist: beets (>=1.4.9)
Requires-Dist: ibroadcast (>=1.1.1)
Requires-Dist: confuse
